<?xml version="1.0" encoding="utf-8"?>
<OBJECT_PROPERTIES>
	<OBJECT_PROPERTY>
		<PROPERTY>x_vahicle_desc</PROPERTY>
		<PROPERTY_DETAIL>Araç Kısayol Butonları Gelsin mi ?</PROPERTY_DETAIL>
		<PROPERTY_TYPE>select</PROPERTY_TYPE>
		<PROPERTY_VALUES>1,0</PROPERTY_VALUES>
		<PROPERTY_NAMES>Evet,Hayır</PROPERTY_NAMES>
		<PROPERTY_DEFAULT>1</PROPERTY_DEFAULT>
		<PROPERTY_HELP>Fiziki varlık kategorisinde rezerve edilir seçilmişse ve bu seçenek de evet olarak seçilirse kısayol butonları gelir.</PROPERTY_HELP>
	</OBJECT_PROPERTY>
	<OBJECT_PROPERTY>
		<PROPERTY>x_vahicle_detail</PROPERTY>
		<PROPERTY_DETAIL>KM Kontrole Açıklama Sütunu Gelsin mi?</PROPERTY_DETAIL>
		<PROPERTY_TYPE>select</PROPERTY_TYPE>
		<PROPERTY_VALUES>1,0</PROPERTY_VALUES>
		<PROPERTY_NAMES>Evet,Hayır</PROPERTY_NAMES>
		<PROPERTY_DEFAULT>1</PROPERTY_DEFAULT>
		<PROPERTY_HELP></PROPERTY_HELP>
	</OBJECT_PROPERTY>
	<OBJECT_PROPERTY>
		<PROPERTY>x_dimension</PROPERTY>
		<PROPERTY_DETAIL>Araçlarda Boyut Kontrolü</PROPERTY_DETAIL>
		<PROPERTY_TYPE>select</PROPERTY_TYPE>
		<PROPERTY_VALUES>1,0</PROPERTY_VALUES>
		<PROPERTY_NAMES>Olsun,Olmasın</PROPERTY_NAMES>
		<PROPERTY_DEFAULT>0</PROPERTY_DEFAULT>
		<PROPERTY_HELP></PROPERTY_HELP>
	</OBJECT_PROPERTY>
	<OBJECT_PROPERTY>
		<PROPERTY>x_new_assetp_group</PROPERTY>
		<PROPERTY_DETAIL>İş Grubu Gelsin mi?</PROPERTY_DETAIL>
		<PROPERTY_TYPE>select</PROPERTY_TYPE>
		<PROPERTY_VALUES>1,0</PROPERTY_VALUES>
		<PROPERTY_NAMES>Evet,Hayır</PROPERTY_NAMES>
		<PROPERTY_DEFAULT>1</PROPERTY_DEFAULT>
		<PROPERTY_HELP></PROPERTY_HELP>
	</OBJECT_PROPERTY>
	<OBJECT_PROPERTY>
		<PROPERTY>x_new_usage_purpose_id</PROPERTY>
		<PROPERTY_DETAIL>Kullanım Amacı Gelsin mi?</PROPERTY_DETAIL>
		<PROPERTY_TYPE>select</PROPERTY_TYPE>
		<PROPERTY_VALUES>1,0</PROPERTY_VALUES>
		<PROPERTY_NAMES>Evet,Hayır</PROPERTY_NAMES>
		<PROPERTY_DEFAULT>1</PROPERTY_DEFAULT>
		<PROPERTY_HELP></PROPERTY_HELP>
	</OBJECT_PROPERTY>
	<OBJECT_PROPERTY>
		<PROPERTY>x_department2</PROPERTY>
		<PROPERTY_DETAIL>Kullanıcı Şube Gelsin mi?</PROPERTY_DETAIL>
		<PROPERTY_TYPE>select</PROPERTY_TYPE>
		<PROPERTY_VALUES>1,0</PROPERTY_VALUES>
		<PROPERTY_NAMES>Evet,Hayır</PROPERTY_NAMES>
		<PROPERTY_DEFAULT>1</PROPERTY_DEFAULT>
		<PROPERTY_HELP></PROPERTY_HELP>
	</OBJECT_PROPERTY>
	<OBJECT_PROPERTY>
		<PROPERTY>x_relation_asset</PROPERTY>
		<PROPERTY_DETAIL>İlişkili Fiziki Varlık Gelsin mi?</PROPERTY_DETAIL>
		<PROPERTY_TYPE>select</PROPERTY_TYPE>
		<PROPERTY_VALUES>1,0</PROPERTY_VALUES>
		<PROPERTY_NAMES>Evet,Hayır</PROPERTY_NAMES>
		<PROPERTY_DEFAULT>1</PROPERTY_DEFAULT>
		<PROPERTY_HELP></PROPERTY_HELP>
	</OBJECT_PROPERTY>
	<OBJECT_PROPERTY>
		<PROPERTY>x_assetp_other_money_value</PROPERTY>
		<PROPERTY_DETAIL>Değer Alanı Gelsin mi?</PROPERTY_DETAIL>
		<PROPERTY_TYPE>select</PROPERTY_TYPE>
		<PROPERTY_VALUES>1,0</PROPERTY_VALUES>
		<PROPERTY_NAMES>Evet,Hayır</PROPERTY_NAMES>
		<PROPERTY_DEFAULT>1</PROPERTY_DEFAULT>
		<PROPERTY_HELP></PROPERTY_HELP>
	</OBJECT_PROPERTY>
	<OBJECT_PROPERTY>
		<PROPERTY>x_assetp_insurance</PROPERTY>
		<PROPERTY_DETAIL>Sigortalar Gelsin mi?</PROPERTY_DETAIL>
		<PROPERTY_TYPE>select</PROPERTY_TYPE>
		<PROPERTY_VALUES>1,0</PROPERTY_VALUES>
		<PROPERTY_NAMES>Evet,Hayır</PROPERTY_NAMES>
		<PROPERTY_DEFAULT>0</PROPERTY_DEFAULT>
		<PROPERTY_HELP></PROPERTY_HELP>
	</OBJECT_PROPERTY>
	<OBJECT_PROPERTY>
		<PROPERTY>x_position_cat_id</PROPERTY>
		<PROPERTY_DETAIL>Pozisyon Tipi Alanı Gelsin mi?</PROPERTY_DETAIL>
		<PROPERTY_TYPE>select</PROPERTY_TYPE>
		<PROPERTY_VALUES>1,0</PROPERTY_VALUES>
		<PROPERTY_NAMES>Evet,Hayır</PROPERTY_NAMES>
		<PROPERTY_DEFAULT>0</PROPERTY_DEFAULT>
		<PROPERTY_HELP></PROPERTY_HELP>
	</OBJECT_PROPERTY>
	<OBJECT_PROPERTY>
		<PROPERTY>x_fill_department</PROPERTY>
		<PROPERTY_DETAIL>Sorumluya Bağlı Olarak Departman Bilgisi Gelsin mi?</PROPERTY_DETAIL>
		<PROPERTY_TYPE>select</PROPERTY_TYPE>
		<PROPERTY_VALUES>1,0</PROPERTY_VALUES>
		<PROPERTY_NAMES>Evet,Hayır</PROPERTY_NAMES>
		<PROPERTY_DEFAULT>0</PROPERTY_DEFAULT>
		<PROPERTY_HELP></PROPERTY_HELP>
	</OBJECT_PROPERTY>
</OBJECT_PROPERTIES>