<?xml version="1.0" encoding="utf-8"?>
<OBJECT_PROPERTIES>
	<OBJECT_PROPERTY>
		<PROPERTY>is_detail_credit_contract</PROPERTY>
		<PROPERTY_DETAIL>Tahsilat ve Ödeme Bilgisi Detaylı Görüntülensin mi?</PROPERTY_DETAIL>
		<PROPERTY_TYPE>select</PROPERTY_TYPE>
		<PROPERTY_VALUES>1,0</PROPERTY_VALUES>
		<PROPERTY_NAMES>Evet,Hayır</PROPERTY_NAMES>
		<PROPERTY_DEFAULT>0</PROPERTY_DEFAULT>
		<PROPERTY_HELP></PROPERTY_HELP>
	</OBJECT_PROPERTY>
	<OBJECT_PROPERTY>
		<PROPERTY>is_agreement_no</PROPERTY>
		<PROPERTY_DETAIL>Sözleşme No Görüntülensin mi?</PROPERTY_DETAIL>
		<PROPERTY_TYPE>select</PROPERTY_TYPE>
		<PROPERTY_VALUES>1,0</PROPERTY_VALUES>
		<PROPERTY_NAMES>Evet,Hayır</PROPERTY_NAMES>
		<PROPERTY_DEFAULT>1</PROPERTY_DEFAULT>
		<PROPERTY_HELP></PROPERTY_HELP>
	</OBJECT_PROPERTY>
	<OBJECT_PROPERTY>
		<PROPERTY>is_credit_employee_id</PROPERTY>
		<PROPERTY_DETAIL>Sorumlu alanları görüntülensin mi?</PROPERTY_DETAIL>
		<PROPERTY_TYPE>select</PROPERTY_TYPE>
		<PROPERTY_VALUES>1,0</PROPERTY_VALUES>
		<PROPERTY_NAMES>Evet,Hayır</PROPERTY_NAMES>
		<PROPERTY_DEFAULT>1</PROPERTY_DEFAULT>
		<PROPERTY_HELP></PROPERTY_HELP>
	</OBJECT_PROPERTY>
</OBJECT_PROPERTIES>