<?xml version="1.0" encoding="utf-8"?>
<OBJECT_PROPERTIES>
	<OBJECT_PROPERTY>
		<PROPERTY>xml_is_create_budget_plan</PROPERTY>
		<PROPERTY_DETAIL>Reeskontun Planlama Fişi Oluşturulsun</PROPERTY_DETAIL>
		<PROPERTY_TYPE>select</PROPERTY_TYPE>
		<PROPERTY_VALUES>1,0</PROPERTY_VALUES>
		<PROPERTY_NAMES>Evet,Hayır</PROPERTY_NAMES>
		<PROPERTY_DEFAULT>1</PROPERTY_DEFAULT>
		<PROPERTY_HELP>Reeskont Sonucunu Planlama Fişine Dönüştürür.</PROPERTY_HELP>
	</OBJECT_PROPERTY>
	<OBJECT_PROPERTY>
		<PROPERTY>xml_is_budget_income_cost</PROPERTY>
		<PROPERTY_DETAIL>Reeskont Gelirleştirilsin</PROPERTY_DETAIL>
		<PROPERTY_TYPE>select</PROPERTY_TYPE>
		<PROPERTY_VALUES>1,0</PROPERTY_VALUES>
		<PROPERTY_NAMES>Evet,Hayır</PROPERTY_NAMES>
		<PROPERTY_DEFAULT>1</PROPERTY_DEFAULT>
		<PROPERTY_HELP>Reeskont Gelirlere Yazılır.</PROPERTY_HELP>
	</OBJECT_PROPERTY>
</OBJECT_PROPERTIES>