<?xml version="1.0" encoding="utf-8"?>
<OBJECT_PROPERTIES>
	<OBJECT_PROPERTY>
		<PROPERTY>add_bank_xml</PROPERTY>
		<PROPERTY_DETAIL>Banka Zorunlu Olsun mu?</PROPERTY_DETAIL>
		<PROPERTY_TYPE>select</PROPERTY_TYPE>
		<PROPERTY_VALUES>1,0</PROPERTY_VALUES>
		<PROPERTY_NAMES>Evet,Hayır</PROPERTY_NAMES>
		<PROPERTY_DEFAULT>0</PROPERTY_DEFAULT>
		<PROPERTY_HELP></PROPERTY_HELP>
	</OBJECT_PROPERTY>
	<OBJECT_PROPERTY>
		<PROPERTY>xml_special_def</PROPERTY>
		<PROPERTY_DETAIL>Özel Tanım Olsun mu?</PROPERTY_DETAIL>
		<PROPERTY_TYPE>select</PROPERTY_TYPE>
		<PROPERTY_VALUES>2,1,0</PROPERTY_VALUES>
		<PROPERTY_NAMES>Zorunlu,Evet,Hayır</PROPERTY_NAMES>
		<PROPERTY_DEFAULT>0</PROPERTY_DEFAULT>
		<PROPERTY_HELP></PROPERTY_HELP>
	</OBJECT_PROPERTY>
</OBJECT_PROPERTIES>