<?xml version="1.0" encoding="utf-8"?>
	<OBJECT_PROPERTIES>
		<OBJECT_PROPERTY>
		<PROPERTY>x_multiple_emp</PROPERTY>
		<PROPERTY_DETAIL>Birden fazla katılımcı eklenebilsin?</PROPERTY_DETAIL>
		<PROPERTY_TYPE>select</PROPERTY_TYPE>
		<PROPERTY_VALUES>1,0</PROPERTY_VALUES>
		<PROPERTY_NAMES>Evet,Hayır</PROPERTY_NAMES>
		<PROPERTY_DEFAULT>0</PROPERTY_DEFAULT>
		<PROPERTY_HELP></PROPERTY_HELP>
	</OBJECT_PROPERTY>
	<OBJECT_PROPERTY>
		<PROPERTY>x_manager_code</PROPERTY>
		<PROPERTY_DETAIL>Onaylayacak Yönetici Pozisyon Kodu</PROPERTY_DETAIL>
		<PROPERTY_TYPE>input</PROPERTY_TYPE>
		<PROPERTY_VALUES></PROPERTY_VALUES>
		<PROPERTY_NAMES></PROPERTY_NAMES>
		<PROPERTY_DEFAULT></PROPERTY_DEFAULT>
		<PROPERTY_HELP></PROPERTY_HELP>
	</OBJECT_PROPERTY>
</OBJECT_PROPERTIES>