<?xml version="1.0" encoding="utf-8"?>
<OBJECT_PROPERTIES>
  <OBJECT_PROPERTY>
		<PROPERTY>xml_show_confirm_selection</PROPERTY>
		<PROPERTY_DETAIL>Onay / Red Seçimi Yapılsın</PROPERTY_DETAIL>
		<PROPERTY_TYPE>select</PROPERTY_TYPE>
		<PROPERTY_VALUES>1,0</PROPERTY_VALUES>
		<PROPERTY_NAMES>Evet,Hayır</PROPERTY_NAMES>
		<PROPERTY_DEFAULT>0</PROPERTY_DEFAULT>
		<PROPERTY_HELP>Aşamanın Onay veya Red Olması Durumu Saklanarak Uyarılarda vb. Kullanılır.</PROPERTY_HELP>
	</OBJECT_PROPERTY>
	<OBJECT_PROPERTY>
		<PROPERTY>xml_show_stage_code</PROPERTY>
		<PROPERTY_DETAIL>Aşama Kodu Gelsin</PROPERTY_DETAIL>
		<PROPERTY_TYPE>select</PROPERTY_TYPE>
		<PROPERTY_VALUES>1,0</PROPERTY_VALUES>
		<PROPERTY_NAMES>Evet,Hayır</PROPERTY_NAMES>
		<PROPERTY_DEFAULT>0</PROPERTY_DEFAULT>
		<PROPERTY_HELP>Aşama Kodu Bilgisi Girilir, Bu Değer Belgede Aşamalarda Görünür.</PROPERTY_HELP>
	</OBJECT_PROPERTY>
</OBJECT_PROPERTIES>