<?xml version="1.0" encoding="utf-8"?>
<OBJECT_PROPERTIES>	
	<OBJECT_PROPERTY>
		<PROPERTY>type_content</PROPERTY>
		<PROPERTY_DETAIL>İçerik Şekli</PROPERTY_DETAIL>
		<PROPERTY_TYPE>select</PROPERTY_TYPE>
		<PROPERTY_VALUES>1,0</PROPERTY_VALUES>
		<PROPERTY_NAMES>Card,Liste</PROPERTY_NAMES>
		<PROPERTY_DEFAULT>0</PROPERTY_DEFAULT>
		<PROPERTY_HELP></PROPERTY_HELP>
	</OBJECT_PROPERTY>
	<OBJECT_PROPERTY>
		<PROPERTY>list_content_width</PROPERTY>
		<PROPERTY_DETAIL>Yan Yana İçerik Sayısı</PROPERTY_DETAIL>
		<PROPERTY_TYPE>select</PROPERTY_TYPE>
		<PROPERTY_VALUES>1,2,3,4,6,12</PROPERTY_VALUES>
		<PROPERTY_NAMES>1,2,3,4,6,12</PROPERTY_NAMES>
		<PROPERTY_DEFAULT>3</PROPERTY_DEFAULT>
		<PROPERTY_HELP></PROPERTY_HELP>
	</OBJECT_PROPERTY>
	<OBJECT_PROPERTY>
		<PROPERTY>is_list_content_header</PROPERTY>
		<PROPERTY_DETAIL>Başlık Görüntülensin</PROPERTY_DETAIL>
		<PROPERTY_TYPE>select</PROPERTY_TYPE>
		<PROPERTY_VALUES>1,0</PROPERTY_VALUES>
		<PROPERTY_NAMES>Evet,Hayır</PROPERTY_NAMES>
		<PROPERTY_DEFAULT>1</PROPERTY_DEFAULT>
		<PROPERTY_HELP></PROPERTY_HELP>
	</OBJECT_PROPERTY>
	<OBJECT_PROPERTY>
		<PROPERTY>list_content_image</PROPERTY>
		<PROPERTY_DETAIL>İmaj Görüntülensin</PROPERTY_DETAIL>
		<PROPERTY_TYPE>select</PROPERTY_TYPE>
		<PROPERTY_VALUES>1,0</PROPERTY_VALUES>
		<PROPERTY_NAMES>Evet,Hayır</PROPERTY_NAMES>
		<PROPERTY_DEFAULT>1</PROPERTY_DEFAULT>
		<PROPERTY_HELP></PROPERTY_HELP>
	</OBJECT_PROPERTY>
	<OBJECT_PROPERTY>
		<PROPERTY>is_list_content_summary</PROPERTY>
		<PROPERTY_DETAIL>Özet Görüntülensin</PROPERTY_DETAIL>
		<PROPERTY_TYPE>select</PROPERTY_TYPE>
		<PROPERTY_VALUES>1,0</PROPERTY_VALUES>
		<PROPERTY_NAMES>Evet,Hayır</PROPERTY_NAMES>
		<PROPERTY_DEFAULT>1</PROPERTY_DEFAULT>
		<PROPERTY_HELP></PROPERTY_HELP>
	</OBJECT_PROPERTY>
	<OBJECT_PROPERTY>
		<PROPERTY>is_list_content_body</PROPERTY>
		<PROPERTY_DETAIL>Detay Görüntülensin</PROPERTY_DETAIL>
		<PROPERTY_TYPE>select</PROPERTY_TYPE>
		<PROPERTY_VALUES>1,0</PROPERTY_VALUES>
		<PROPERTY_NAMES>Evet,Hayır</PROPERTY_NAMES>
		<PROPERTY_DEFAULT>1</PROPERTY_DEFAULT>
		<PROPERTY_HELP></PROPERTY_HELP>
	</OBJECT_PROPERTY>		
	<OBJECT_PROPERTY>
		<PROPERTY>list_content_maxrow</PROPERTY>
		<PROPERTY_DETAIL>İçerik Sayısı</PROPERTY_DETAIL>
		<PROPERTY_TYPE>input</PROPERTY_TYPE>
		<PROPERTY_VALUES></PROPERTY_VALUES>
		<PROPERTY_NAMES></PROPERTY_NAMES>
		<PROPERTY_DEFAULT>5</PROPERTY_DEFAULT>
		<PROPERTY_HELP></PROPERTY_HELP>
	</OBJECT_PROPERTY>	
</OBJECT_PROPERTIES>