<?xml version="1.0" encoding="utf-8"?>
<OBJECT_PROPERTIES>
	<OBJECT_PROPERTY>
		<PROPERTY>stock_id</PROPERTY>
		<PROPERTY_DETAIL>İş İhaleye Çıkabilir ise stok id girin</PROPERTY_DETAIL>
		<PROPERTY_TYPE>input</PROPERTY_TYPE>
		<PROPERTY_VALUES></PROPERTY_VALUES>
		<PROPERTY_NAMES></PROPERTY_NAMES>
		<PROPERTY_DEFAULT></PROPERTY_DEFAULT>
		<PROPERTY_HELP>İş İhaleye Çıkabilir ise ihale satırında hangi ürün yer alacaksa onun stok idsi girilmeli</PROPERTY_HELP>
	</OBJECT_PROPERTY>
	<OBJECT_PROPERTY>
		<PROPERTY>x_content_id</PROPERTY>
		<PROPERTY_DETAIL>İhale Sözleşme içerik id</PROPERTY_DETAIL>
		<PROPERTY_TYPE>input</PROPERTY_TYPE>
		<PROPERTY_VALUES></PROPERTY_VALUES>
		<PROPERTY_NAMES></PROPERTY_NAMES>
		<PROPERTY_DEFAULT></PROPERTY_DEFAULT>
		<PROPERTY_HELP>Sözleşme metninin yazılı olduğu içeriğin id değerini giriniz</PROPERTY_HELP>
	</OBJECT_PROPERTY>
</OBJECT_PROPERTIES>